README.md
setup.py
molgif/__init__.py
molgif/_version.py
molgif/command_line.py
molgif/gifmaker.py
molgif/molecule.py
molgif/utils.py
molgif.egg-info/PKG-INFO
molgif.egg-info/SOURCES.txt
molgif.egg-info/dependency_links.txt
molgif.egg-info/entry_points.txt
molgif.egg-info/requires.txt
molgif.egg-info/top_level.txt