Metadata-Version: 2.1
Name: molgif
Version: 0.3.6
Summary: creates smooth gifs of rotating molecules
Home-page: https://www.github.com/michael-cowan/molgif
Author: Michael Cowan
License: UNKNOWN
Platform: UNKNOWN
Requires-Python: >=3.5
